mondrianish/__init__.py
mondrianish-0.5.3.dist-info/DESCRIPTION.rst
mondrianish-0.5.3.dist-info/METADATA
mondrianish-0.5.3.dist-info/RECORD
mondrianish-0.5.3.dist-info/WHEEL
mondrianish-0.5.3.dist-info/entry_points.txt
mondrianish-0.5.3.dist-info/metadata.json
mondrianish-0.5.3.dist-info/top_level.txt
