Metadata-Version: 2.0
Name: mondrianish
Version: 0.5.3
Summary: Generate Piet Mondrian-style images.
Home-page: https://github.com/GovReady/mondrianish
Author: GovReady PBC
Author-email: jt@occams.info
License: CC0 1.0 Universal
Platform: UNKNOWN
Requires-Dist: pillow
Requires-Dist: colour
